pipxl/__about__.py
pipxl/__init__.py
pipxl/compile.py
pipxl/data.py
pipxl/deptree.py
pipxl/license.py
pipxl/pip_cli.py
pipxl/resolver.py
pipxl/sync.py
pipxl/cli/__init__.py
pipxl-0.0.4.dist-info/METADATA
pipxl-0.0.4.dist-info/WHEEL
pipxl-0.0.4.dist-info/entry_points.txt
pipxl-0.0.4.dist-info/licenses/LICENSE.txt
pipxl-0.0.4.dist-info/RECORD
