Metadata-Version: 2.1
Name: pipxl
Version: 0.0.4
Summary: Additional tools for pip - compile, sync, deptree & license
Project-URL: Documentation, https://github.com/zundertj/pipxl#readme
Project-URL: Issues, https://github.com/zundertj/pipxl/issues
Project-URL: Source, https://github.com/zundertj/pipxl
Author-email: Jeroen van Zundert <mail@jeroenvanzundert.nl>
License-File: LICENSE.txt
Classifier: Development Status :: 4 - Beta
Classifier: Intended Audience :: Developers
Classifier: License :: OSI Approved :: MIT License
Classifier: Operating System :: OS Independent
Classifier: Programming Language :: Python
Classifier: Programming Language :: Python :: 3.7
Classifier: Programming Language :: Python :: 3.8
Classifier: Programming Language :: Python :: 3.9
Classifier: Programming Language :: Python :: 3.10
Classifier: Programming Language :: Python :: 3.11
Classifier: Programming Language :: Python :: Implementation :: CPython
Classifier: Programming Language :: Python :: Implementation :: PyPy
Requires-Python: >=3.7
Requires-Dist: pip>=22.2.2
Requires-Dist: typer>=0.4.2
